liyiproject/DiskInfo.py
liyiproject/LoadsInfo.py
liyiproject/NetworkInfo.py
liyiproject/__init__.py
liyiproject/liyiproject.py
liyiproject-0.0.11.dist-info/METADATA
liyiproject-0.0.11.dist-info/WHEEL
liyiproject-0.0.11.dist-info/licenses/LICENSE
liyiproject-0.0.11.dist-info/RECORD
